pytransform3d/__init__.py
pytransform3d/_geometry.py
pytransform3d/_geometry.pyi
pytransform3d/_mesh_loader.py
pytransform3d/_mesh_loader.pyi
pytransform3d/camera.py
pytransform3d/camera.pyi
pytransform3d/coordinates.py
pytransform3d/coordinates.pyi
pytransform3d/editor.py
pytransform3d/py.typed
pytransform3d/urdf.py
pytransform3d/urdf.pyi
pytransform3d/batch_rotations/__init__.py
pytransform3d/batch_rotations/_angle.py
pytransform3d/batch_rotations/_angle.pyi
pytransform3d/batch_rotations/_axis_angle.py
pytransform3d/batch_rotations/_axis_angle.pyi
pytransform3d/batch_rotations/_euler.py
pytransform3d/batch_rotations/_euler.pyi
pytransform3d/batch_rotations/_matrix.py
pytransform3d/batch_rotations/_matrix.pyi
pytransform3d/batch_rotations/_quaternion.py
pytransform3d/batch_rotations/_quaternion.pyi
pytransform3d/batch_rotations/_utils.py
pytransform3d/batch_rotations/_utils.pyi
pytransform3d/plot_utils/__init__.py
pytransform3d/plot_utils/_artists.py
pytransform3d/plot_utils/_artists.pyi
pytransform3d/plot_utils/_layout.py
pytransform3d/plot_utils/_layout.pyi
pytransform3d/plot_utils/_plot_geometries.py
pytransform3d/plot_utils/_plot_geometries.pyi
pytransform3d/plot_utils/_plot_helpers.py
pytransform3d/plot_utils/_plot_helpers.pyi
pytransform3d/rotations/__init__.py
pytransform3d/rotations/_angle.py
pytransform3d/rotations/_angle.pyi
pytransform3d/rotations/_axis_angle.py
pytransform3d/rotations/_axis_angle.pyi
pytransform3d/rotations/_constants.py
pytransform3d/rotations/_euler.py
pytransform3d/rotations/_euler.pyi
pytransform3d/rotations/_euler_deprecated.py
pytransform3d/rotations/_euler_deprecated.pyi
pytransform3d/rotations/_jacobians.py
pytransform3d/rotations/_jacobians.pyi
pytransform3d/rotations/_matrix.py
pytransform3d/rotations/_matrix.pyi
pytransform3d/rotations/_mrp.py
pytransform3d/rotations/_mrp.pyi
pytransform3d/rotations/_plot.py
pytransform3d/rotations/_plot.pyi
pytransform3d/rotations/_polar_decomp.py
pytransform3d/rotations/_polar_decomp.pyi
pytransform3d-3.14.3.dist-info/licenses/LICENSE
pytransform3d-3.14.3.dist-info/METADATA
pytransform3d-3.14.3.dist-info/WHEEL
pytransform3d-3.14.3.dist-info/top_level.txt
pytransform3d-3.14.3.dist-info/RECORD
