Metadata-Version: 2.4
Name: pytransform3d
Version: 3.14.3
Summary: 3D transformations for Python
Home-page: https://github.com/dfki-ric/pytransform3d
Author: Alexander Fabisch
Author-email: afabisch@googlemail.com
License: BSD-3-Clause
Classifier: Programming Language :: Python :: 2
Classifier: Programming Language :: Python :: 3
Classifier: License :: OSI Approved :: BSD License
Classifier: Operating System :: OS Independent
Classifier: Topic :: Scientific/Engineering :: Mathematics
Classifier: Topic :: Scientific/Engineering :: Visualization
License-File: LICENSE
Requires-Dist: numpy
Requires-Dist: scipy
Requires-Dist: matplotlib
Requires-Dist: lxml
Provides-Extra: all
Requires-Dist: pydot; extra == "all"
Requires-Dist: trimesh; extra == "all"
Requires-Dist: pycollada; extra == "all"
Requires-Dist: open3d; extra == "all"
Provides-Extra: doc
Requires-Dist: numpydoc; extra == "doc"
Requires-Dist: sphinx; extra == "doc"
Requires-Dist: sphinx-gallery; extra == "doc"
Requires-Dist: pydata-sphinx-theme; extra == "doc"
Requires-Dist: sphinxcontrib.video; extra == "doc"
Provides-Extra: test
Requires-Dist: pytest; extra == "test"
Requires-Dist: pytest-cov; extra == "test"
Dynamic: author
Dynamic: author-email
Dynamic: classifier
Dynamic: description
Dynamic: description-content-type
Dynamic: home-page
Dynamic: license
Dynamic: license-file
Dynamic: provides-extra
Dynamic: requires-dist
Dynamic: summary
